frequenpy/__init__.py
frequenpy/cli.py
frequenpy/beaded_string/__init__.py
frequenpy/beaded_string/animation.py
frequenpy/beaded_string/beaded_string.py
frequenpy/beaded_string/beaded_string_factory.py
frequenpy-0.2.1.dist-info/LICENSE
frequenpy-0.2.1.dist-info/METADATA
frequenpy-0.2.1.dist-info/WHEEL
frequenpy-0.2.1.dist-info/entry_points.txt
frequenpy-0.2.1.dist-info/top_level.txt
frequenpy-0.2.1.dist-info/RECORD
