Metadata-Version: 2.1
Name: frequenpy
Version: 0.2.1
Summary: Physics engine for standing waves
Home-page: https://github.com/tomasjuanlink/frequenpy
Author: Tomás Juan Link
Author-email: tomaslink@gmail.com
License: UNKNOWN
Platform: UNKNOWN
Classifier: Programming Language :: Python :: 3.5
Classifier: Programming Language :: Python :: 3.6
Classifier: Programming Language :: Python :: 3.7
Classifier: License :: OSI Approved :: GNU General Public License v3 (GPLv3)
Classifier: Operating System :: OS Independent
Requires-Dist: numpy (==1.15.4)
Requires-Dist: matplotlib (==3.0.2)
